README.md
setup.py
boost_siper.egg-info/PKG-INFO
boost_siper.egg-info/SOURCES.txt
boost_siper.egg-info/dependency_links.txt
boost_siper.egg-info/requires.txt
boost_siper.egg-info/top_level.txt
boost_spider/__init__.py
boost_spider/http/__init__.py
boost_spider/http/request_client.py
boost_spider/http/user_agent.py